pcvis/__init__.py
pcvis/pcvis.py
pcvis-0.6.1.dist-info/LICENSE
pcvis-0.6.1.dist-info/METADATA
pcvis-0.6.1.dist-info/WHEEL
pcvis-0.6.1.dist-info/entry_points.txt
pcvis-0.6.1.dist-info/RECORD
